indico_importer/__init__.py
indico_importer/base.py
indico_importer/controllers.py
indico_importer/converter.py
indico_importer/plugin.py
indico_importer/util.py
indico_importer/static/dist/manifest.json
indico_importer/static/dist/css/main.f57f5fc2.css
indico_importer/static/dist/css/main.f57f5fc2.css.map
indico_importer/static/dist/js/main.6057b57b.bundle.js
indico_importer/static/dist/js/main.6057b57b.bundle.js.map
indico_importer/translations/messages-js.pot
indico_importer/translations/messages.pot
indico_importer/translations/fr_FR/LC_MESSAGES/messages-js.po
indico_importer/translations/fr_FR/LC_MESSAGES/messages.mo
indico_importer/translations/fr_FR/LC_MESSAGES/messages.po
indico_plugin_importer-2.2.dist-info/METADATA
indico_plugin_importer-2.2.dist-info/WHEEL
indico_plugin_importer-2.2.dist-info/entry_points.txt
indico_plugin_importer-2.2.dist-info/top_level.txt
indico_plugin_importer-2.2.dist-info/RECORD
