Metadata-Version: 2.1
Name: indico-plugin-importer
Version: 2.2
Summary: Framework for importing timetable data from external sources into Indico
Home-page: https://github.com/indico/indico-plugins
Author: Indico Team
Author-email: indico-team@cern.ch
License: MIT
Platform: UNKNOWN
Classifier: Environment :: Plugins
Classifier: Environment :: Web Environment
Classifier: License :: OSI Approved :: MIT License
Classifier: Programming Language :: Python :: 2.7
Requires-Dist: indico (>=2.2.dev0)
